leonardo_api/__init__.py
leonardo_api/leonardo_async.py
leonardo_api/leonardo_sync.py
leonardo_api/logger_config.py
leonardo_api/models.py
leonardo_api-0.0.11.dist-info/METADATA
leonardo_api-0.0.11.dist-info/WHEEL
leonardo_api-0.0.11.dist-info/licenses/LICENSE
leonardo_api-0.0.11.dist-info/RECORD
